Workbook

Sheet README
A1: Discovery ROI calculator
A3: Partner-editable workbook that turns discovery answers into a signed-off ROI hypothesis and a copy-guide for the kpis[] block in accelerator.yaml.
A5: How to use:
A6: 1. Open 'Inputs' and fill every BLUE cell. YELLOW-highlighted cells are must-fill.
A7: 2. Read 'ROI' for annual savings, payback, and 3-year cumulative impact.
A8: 3. Read 'KPIs' — rows 5-7 render baseline/target values; hand-copy them into
A9: accelerator.yaml:kpis[] using the template in row 14. (Not paste-ready —
A10: Excel does not expand cell addresses into text when you copy out of a cell.)
A11: 4. Attach this file to docs/discovery/solution-brief.md §4 as the ROI hypothesis source.
A13: Conventions (industry-standard financial-model colors):
A14: BLUE cells = hardcoded inputs you edit per customer
A15: BLACK cells = formulas (do not hand-edit)
... A35: * docs/discovery/how-to-use.md — sequencing across all five artifacts

Sheet Inputs
A1: Inputs
A2: Edit BLUE cells. Units are noted per row. Cells with YELLOW fill are must-fill; leaving them blank leaves ROI at zero.
A4: Input | B4: Value | C4: Unit | D4: Notes
A5: 1. Engagement framing
A6: Customer name | B6: Contoso Manufacturing, Inc. | C6: text | D6: Used on every sheet header. Partner fills during kickoff.
A7: Engagement start date | B7: 46142 | C7: date | D7: Anchor for 1Y / 3Y savings projections.
A8: Analysis horizon | B8: 3 | C8: years | D8: Default 3 years; edit if customer's business case runs longer.
A9: Discount rate (annual) | B9: 0.08 | C9: ratio | D9: WACC or partner-standard hurdle rate. 0.08 = 8%.
A10: 2. Manual status-quo cost
A11: FTEs doing this work today | B11: 14 | C11: count | D11: Integer count. Include only FTEs whose time the agent displaces.
A12: Fully-loaded annual cost per FTE | B12: 145000 | C12: $/yr | D12: Base + benefits + overhead. Use customer HR figure if shared; else market proxy.
A13: % of FTE time spent on this process | B13: 0.6 | C13: ratio | D13: 0.0 – 1.0. Default 0.5 = half of each person's time is on this process.
A14: Transactions per year (if different denominator) | B14: 0 | C14: count | D14: Leave 0 if FTE-based. Only filled if cost model is $/transaction × volume.
A15: Cost per transaction (manual, if using that model) | B15: 0 | C15: $/txn | D15: Leave 0 if FTE-based. Pairs with the row above.
A16: 3. Agent target performance
A17: Time per task today (manual) | B17: 110 | C17: minutes | D17: Median, not best case. Feeds briefing_production_time KPI.
A18: Time per task with agent (target) | B18: 18 | C18: minutes | D18: Target after GA. Must be achievable under acceptance.p95_latency_ms.
A19: Target % of cases agent handles end-to-end | B19: 0.72 | C19: ratio | D19: The rest stay human or route through HITL. 0.0 – 1.0.
A20: HITL approval rate (target) | B20: 0.88 | C20: ratio | D20: Fraction of agent drafts expected to ship as-is after review. Mirrors accelerator.yaml:kpis.hitl_approval_rate.
A21: 4. Azure + agent run cost
A22: Estimated Azure run cost (monthly) | B22: 13500 | C22: $/mo | D22: Placeholder. Refine using Azure pricing calculator after /configure-landing-zone.
A23: Cost per agent call (target) | B23: 0.42 | C23: $/call | D23: Must be ≤ accelerator.yaml:acceptance.cost_per_call_usd. Default matches shipped 0.40.
A24: Monthly agent call volume | B24: 1200 | C24: calls/mo | D24: Expected steady-state call volume post-GA. Drives run-cost sanity check.
A25: 5. Optional revenue lift
A26: Target revenue lift (annual, if attributable) | B26: 0 | C26: $/yr | D26: Often unknown at discovery. Leave 0 unless customer has attribution data.

Sheet ROI
A1: ROI model
A2: Formulas reference "Inputs" (GREEN = cross-sheet link). Revisit after pilot to reconcile against measured performance.
A4: A. Manual status-quo annual cost
A5: FTE-based component | B5: =Inputs!$B$11*Inputs!$B$12*Inputs!$B$13 -> 1218000
A6: Transaction-based component | B6: =Inputs!$B$14*Inputs!$B$15 -> 0
A7: Total manual cost (annual) | B7: =B5+B6 -> 1218000
A9: B. Agent annual run cost
A10: Annual Azure run cost (infra) | B10: =Inputs!$B$22*12 -> 162000
A11: Annual agent call cost (LLM + tool) | B11: =Inputs!$B$24*12*Inputs!$B$23 -> 6048
A12: Total agent run cost (annual) | B12: =B10+B11 -> 168048
A14: C. Annual impact
A15: Labor savings (coverage × manual cost) | B15: =Inputs!$B$19*B7 -> 876960
A16: Revenue lift (input) | B16: =Inputs!$B$26 -> 0
A17: Gross annual benefit | B17: =B15+B16 -> 876960
A18: Less: agent run cost | B18: =-B12 -> -168048
A19: Net annual impact | B19: =B17+B18 -> 708912
A21: D. Payback & NPV
A22: One-time implementation cost (optional) | B22: 180000 | C22: edit if partner has a fixed-fee component
A23: Simple payback (months) | B23: =IFERROR(IF(ISBLANK(B19),"fill inputs",IF(B19=0,"fill inputs",IF(B19<0,"no payback at current inputs",B22/B19*12))),"fill inputs") -> 3.0469226 | C23: Shows 'no payback at current inputs' if annual impact is negative.
A24: 3-year cumulative net impact | B24: =B19*MIN(Inputs!$B$8,3)-B22 -> 1946736
A25: NPV over horizon | B25: =IFERROR(B19*((1-(1+Inputs!$B$9)^-Inputs!$B$8)/Inputs!$B$9)-B22,"fill inputs") -> 1646935
A27: E. Yearly cashflow schedule (up to 5 years)
A28: Year | B28: Net impact | C28: Discount factor | D28: PV of year | E28: Cumulative PV
A29: Year 1 | B29: =IF(Inputs!$B$8>=1,B19,0) -> 708912 | C29: =IF(Inputs!$B$8>=1,1/(1+Inputs!$B$9)^1,0) -> 0.92592593 | D29: =B29*C29 -> 656400 | E29: =D29-B22 -> 476400
A30: Year 2 | B30: =IF(Inputs!$B$8>=2,B19,0) -> 708912 | C30: =IF(Inputs!$B$8>=2,1/(1+Inputs!$B$9)^2,0) -> 0.85733882 | D30: =B30*C30 -> 607777.78 | E30: =E29+D30 -> 1084177.8
A31: Year 3 | B31: =IF(Inputs!$B$8>=3,B19,0) -> 708912 | C31: =IF(Inputs!$B$8>=3,1/(1+Inputs!$B$9)^3,0) -> 0.79383224 | D31: =B31*C31 -> 562757.2 | E31: =E30+D31 -> 1646935
A32: Year 4 | B32: =IF(Inputs!$B$8>=4,B19,0) -> 0 | C32: =IF(Inputs!$B$8>=4,1/(1+Inputs!$B$9)^4,0) -> 0 | D32: =B32*C32 -> 0 | E32: =E31+D32 -> 1646935
A33: Year 5 | B33: =IF(Inputs!$B$8>=5,B19,0) -> 0 | C33: =IF(Inputs!$B$8>=5,1/(1+Inputs!$B$9)^5,0) -> 0 | D33: =B33*C33 -> 0 | E33: =E32+D33 -> 1646935

Sheet KPIs
A1: KPI copy-guide — hand-copy values from rows 5-7 into accelerator.yaml:kpis
A2: Mirrors the kpis[] schema: {name, type, baseline, target}. Only duration_ms and ratio are wired into src/accelerator_baseline/telemetry.py today; other types require partner code.
A4: KPI event name | B4: type | C4: baseline | D4: target | E4: Notes
A5: supplier_review_cycle_time | B5: duration_ms | C5: =Inputs!$B$17*60*1000 -> 6600000 | D5: =Inputs!$B$18*60*1000 -> 1080000 | E5: Time from supplier review intake to analyst-ready recommendation. Sourced from Inputs section 3.
A6: autonomous_triage_coverage | B6: ratio | C6: 0 | D6: =Inputs!$B$19 -> 0.72 | E6: Fraction of supplier-review cases handled end-to-end through draft recommendation with HITL.
A7: hitl_approval_rate | B7: ratio | C7: 1 | D7: =Inputs!$B$20 -> 0.88 | E7: Fraction of agent drafts approved as-is after human review.
A11: Copy guide — hand-copy the numeric values from rows 5-7 above
A12: After you fill Inputs, each row above renders a baseline and target value. Hand-copy those numbers into accelerator.yaml:kpis using the template below. This is NOT a paste-ready block — Excel does not expand cell addresses into values when you copy text out of a cell.
A14: kpis: - name: supplier_review_cycle_time type: duration_ms baseline: <copy C5 as integer ms> target: <copy D5 as integer ms> - name: autonomous_triage_coverage type: ratio baseline: 0.0 target: <copy D6 as decimal, e.g. 0.72> - name: hitl_approval_rate type: ratio baseline: 1.0 target: <copy D7 as decimal, e.g. 0.88> # cost_per_call_usd belongs in accelerator.yaml:acceptance, not kpis[]. # acceptance.cost_per_call_usd: <copy Inputs!B23 as decimal>
